jjws_package_template/__init__.py
jjws_package_template/example_module/__init__.py
jjws_package_template/example_module/example_file.py
jjws_package_template/scripts/__init__.py
jjws_package_template/scripts/python_publish_example.py
jjws_package_template-0.0.6.dist-info/LICENSE
jjws_package_template-0.0.6.dist-info/METADATA
jjws_package_template-0.0.6.dist-info/WHEEL
jjws_package_template-0.0.6.dist-info/entry_points.txt
jjws_package_template-0.0.6.dist-info/top_level.txt
jjws_package_template-0.0.6.dist-info/RECORD
